odoo/addons/purchase_supplier_rank/README.rst
odoo/addons/purchase_supplier_rank/__init__.py
odoo/addons/purchase_supplier_rank/__manifest__.py
odoo/addons/purchase_supplier_rank/i18n/es.po
odoo/addons/purchase_supplier_rank/i18n/it.po
odoo/addons/purchase_supplier_rank/i18n/purchase_supplier_rank.pot
odoo/addons/purchase_supplier_rank/models/__init__.py
odoo/addons/purchase_supplier_rank/models/purchase_order.py
odoo/addons/purchase_supplier_rank/readme/CONTRIBUTORS.md
odoo/addons/purchase_supplier_rank/readme/DESCRIPTION.md
odoo/addons/purchase_supplier_rank/static/description/icon.png
odoo/addons/purchase_supplier_rank/static/description/index.html
odoo/addons/purchase_supplier_rank/tests/__init__.py
odoo/addons/purchase_supplier_rank/tests/test_purchase_supplier_rank.py
odoo_addon_purchase_supplier_rank-18.0.1.0.0.2.dist-info/METADATA
odoo_addon_purchase_supplier_rank-18.0.1.0.0.2.dist-info/WHEEL
odoo_addon_purchase_supplier_rank-18.0.1.0.0.2.dist-info/top_level.txt
odoo_addon_purchase_supplier_rank-18.0.1.0.0.2.dist-info/RECORD
